odoo8_addon_purchase_supplier_rounding_method_triple_discount-8.0.1.0.0.99.dev2-py2.7-nspkg.pth
odoo8_addon_purchase_supplier_rounding_method_triple_discount-8.0.1.0.0.99.dev2.dist-info/METADATA
odoo8_addon_purchase_supplier_rounding_method_triple_discount-8.0.1.0.0.99.dev2.dist-info/RECORD
odoo8_addon_purchase_supplier_rounding_method_triple_discount-8.0.1.0.0.99.dev2.dist-info/WHEEL
odoo8_addon_purchase_supplier_rounding_method_triple_discount-8.0.1.0.0.99.dev2.dist-info/namespace_packages.txt
odoo8_addon_purchase_supplier_rounding_method_triple_discount-8.0.1.0.0.99.dev2.dist-info/top_level.txt
odoo_addons/purchase_supplier_rounding_method_triple_discount/README.rst
odoo_addons/purchase_supplier_rounding_method_triple_discount/__init__.py
odoo_addons/purchase_supplier_rounding_method_triple_discount/__openerp__.py
odoo_addons/purchase_supplier_rounding_method_triple_discount/i18n/purchase_supplier_rounding_method_triple_discount.pot
odoo_addons/purchase_supplier_rounding_method_triple_discount/models/__init__.py
odoo_addons/purchase_supplier_rounding_method_triple_discount/models/account_invoice_line.py
odoo_addons/purchase_supplier_rounding_method_triple_discount/models/purchase_order_line.py
odoo_addons/purchase_supplier_rounding_method_triple_discount/static/description/icon.png
odoo_addons/purchase_supplier_rounding_method_triple_discount/tests/__init__.py
odoo_addons/purchase_supplier_rounding_method_triple_discount/tests/test_module.py
